code_knowledge_graph-0.1.5.dist-info/licenses/LICENSE
core/__init__.py
core/graph.py
core/scanner.py
core/tree.py
core/parsers/__init__.py
core/parsers/base.py
core/parsers/go_parser.py
core/parsers/js_parser.py
core/parsers/python_parser.py
core/parsers/vue_parser.py
core/services/__init__.py
core/services/call_chain.py
core/services/complexity_analyzer.py
core/services/dead_code_finder.py
core/services/dependency_analysis.py
core/services/embedding_provider.py
core/services/entry_point.py
core/services/function_analysis.py
core/services/go_interface.py
core/services/layer_checker.py
core/services/llm_provider.py
core/services/project.py
core/services/related_context.py
core/services/skeleton.py
core/services/stats.py
core/services/summarizer.py
core/services/symbol_search.py
core/services/usage_finder.py
core/storage/__init__.py
core/storage/base.py
core/storage/sqlite.py
core/storage/sqlite/__init__.py
core/storage/sqlite/call_ops.py
core/storage/sqlite/error_ops.py
core/storage/sqlite/file_ops.py
core/storage/sqlite/go_ops.py
core/storage/sqlite/migration.py
core/storage/sqlite/project_ops.py
core/storage/sqlite/schema.py
core/storage/sqlite/stats_ops.py
core/storage/sqlite/summary_ops.py
core/storage/sqlite/symbol_ops.py
core/storage/sqlite/transaction.py
mcp_server/__init__.py
mcp_server/run.py
mcp_server/tools/__init__.py
mcp_server/tools/base.py
mcp_server/tools/context.py
mcp_server/tools/enhanced.py
mcp_server/tools/guide.py
mcp_server/tools/project.py
mcp_server/tools/stats.py
mcp_server/tools/tool_guides.json
web/__init__.py
web/server.py
web/templates/index.html
code_knowledge_graph-0.1.5.dist-info/METADATA
code_knowledge_graph-0.1.5.dist-info/WHEEL
code_knowledge_graph-0.1.5.dist-info/entry_points.txt
code_knowledge_graph-0.1.5.dist-info/top_level.txt
code_knowledge_graph-0.1.5.dist-info/RECORD
