Metadata-Version: 2.4
Name: code-knowledge-graph
Version: 0.1.5
Summary: Code dependency knowledge graph analyzer with MCP server support
Author-email: qshm <qshm1128@gmail.com>
License: MIT
Project-URL: Homepage, https://github.com/yourusername/code-knowledge-graph
Project-URL: Repository, https://github.com/yourusername/code-knowledge-graph
Keywords: mcp,code-analysis,knowledge-graph,ai,dependency
Classifier: Development Status :: 4 - Beta
Classifier: Intended Audience :: Developers
Classifier: License :: OSI Approved :: MIT License
Classifier: Programming Language :: Python :: 3.12
Classifier: Topic :: Software Development :: Libraries
Requires-Python: >=3.12
License-File: LICENSE
Requires-Dist: ast-grep-py>=0.31.0
Requires-Dist: fastapi>=0.115.0
Requires-Dist: uvicorn>=0.32.0
Requires-Dist: jinja2>=3.1.0
Requires-Dist: httpx>=0.27.0
Requires-Dist: fastmcp>=2.0.0
Provides-Extra: dev
Requires-Dist: pytest>=8.0.0; extra == "dev"
Requires-Dist: pytest-asyncio>=0.23.0; extra == "dev"
Requires-Dist: hypothesis>=6.100.0; extra == "dev"
Dynamic: license-file
